pyfang/__init__.py
pyfang/attributes.py
pyfang/baseStyle copy.py
pyfang/base_style.py
pyfang/component.py
pyfang/tags.py
pyfang-0.1.0.dist-info/LICENSE
pyfang-0.1.0.dist-info/METADATA
pyfang-0.1.0.dist-info/WHEEL
pyfang-0.1.0.dist-info/top_level.txt
pyfang-0.1.0.dist-info/RECORD
